ecl_django/__init__.py
ecl_django/decorators.py
ecl_django/forms.py
ecl_django/metadata.py
ecl_django/models.py
ecl_django/runner.py
ecl_django/settings.py
ecl_django/storages.py
ecl_django/urls.py
ecl_django/utils.py
ecl_django/views.py
ecl_django/management/__init__.py
ecl_django/management/commands/__init__.py
ecl_django/management/commands/create_iam_roles.py
ecl_django/management/commands/deploy.py
ecl_django/management/commands/ecl_test.py
ecl_django/management/commands/syncmedia.py
ecl_django-2.0.4.dist-info/LICENSE
ecl_django-2.0.4.dist-info/METADATA
ecl_django-2.0.4.dist-info/WHEEL
ecl_django-2.0.4.dist-info/top_level.txt
ecl_django-2.0.4.dist-info/RECORD
