Metadata-Version: 2.1
Name: ecl-django
Version: 2.0.4
Summary: Django decorators and some other utilities.
Home-page: https://bitbucket.org/elmcitylabs/ecl-django/src/master/
Author: Dan Loewenherz
Author-email: dan@elmcitylabs.com
License: Apache 2.0
Platform: UNKNOWN
Requires-Dist: django (>=3.0)
Requires-Dist: py-bcrypt
Requires-Dist: ecl-tools (>=1.0.1)
